jqmc/__init__.py
jqmc/_version.py
jqmc/atomic_orbital.py
jqmc/coulomb_potential.py
jqmc/determinant.py
jqmc/diff_mask.py
jqmc/function_collections.py
jqmc/hamiltonians.py
jqmc/header_footer.py
jqmc/jastrow_factor.py
jqmc/jqmc_cli.py
jqmc/jqmc_gfmc.py
jqmc/jqmc_mcmc.py
jqmc/jqmc_miscs.py
jqmc/jqmc_tool.py
jqmc/jqmc_utility.py
jqmc/molecular_orbital.py
jqmc/setting.py
jqmc/structure.py
jqmc/swct.py
jqmc/trexio_wrapper.py
jqmc/wavefunction.py
jqmc-0.1.0a3.dist-info/licenses/LICENSE
jqmc-0.1.0a3.dist-info/METADATA
jqmc-0.1.0a3.dist-info/WHEEL
jqmc-0.1.0a3.dist-info/entry_points.txt
jqmc-0.1.0a3.dist-info/top_level.txt
jqmc-0.1.0a3.dist-info/RECORD
