Metadata-Version: 2.4
Name: jqmc
Version: 0.1.0a3
Home-page: https://github.com/kousuke-nakano/jQMC
Author: Kosuke Nakano
Author-email: kousuke_1123@icloud.com
Project-URL: Bug tracker, https://github.com/kousuke-nakano/jQMC/issues
Project-URL: Documentations, https://jQMC.readthedocs.io/en/latest/
Classifier: Intended Audience :: Science/Research
Classifier: Programming Language :: Python :: 3.10
Classifier: Programming Language :: Python :: 3.11
Classifier: Programming Language :: Python :: 3.12
Classifier: License :: OSI Approved :: BSD License
Classifier: Operating System :: OS Independent
Classifier: Topic :: Scientific/Engineering :: Mathematics
Classifier: Topic :: Scientific/Engineering :: Physics
Requires-Python: >=3.10.0
License-File: LICENSE
Requires-Dist: numpy>=1.26.4
Requires-Dist: scipy>=1.12.0
Requires-Dist: jax<0.8.0,>=0.6.0
Requires-Dist: jaxlib<0.8.0,>=0.6.0
Requires-Dist: jaxtyping<0.4.0,>=0.2.29
Requires-Dist: flax<0.11.0,>=0.8.3
Requires-Dist: optax<0.3.0,>=0.2.0
Requires-Dist: mpi4jax<0.9.0,>=0.7.0
Requires-Dist: mpi4py>=4.0.2
Requires-Dist: trexio>=2.6.0
Requires-Dist: pytest>=8.3.5
Requires-Dist: pre-commit>=4.0.2
Requires-Dist: setuptools_scm>=8.1.2
Requires-Dist: toml>=0.10.2
Requires-Dist: typer>=0.15.1
Requires-Dist: tomlkit>=0.13.2
Requires-Dist: uncertainties>=3.2.2
Requires-Dist: matplotlib>=3.10.1
Requires-Dist: h5py>=3.10.0
Dynamic: license-file
